LICENSE.txt
MANIFEST.in
README.rst
setup.py
alarm/__init__.py
alarm/begin.py
pyAlarm.egg-info/PKG-INFO
pyAlarm.egg-info/SOURCES.txt
pyAlarm.egg-info/dependency_links.txt
pyAlarm.egg-info/top_level.txt