Metadata-Version: 1.1
Name: pyAlarm
Version: 1.0.1
Summary: Run Alarm on cli or in Background.
Home-page: https://github.com/famishedrover/AlarmClock
Author: Angryziber
Author-email: mudit.verma2014@gmail.com
License: MIT
Keywords: Alarm Python Threading
Platform: UNKNOWN
Classifier: Development Status :: 3 - Alpha
Classifier: Intended Audience :: Developers
Classifier: Topic :: Software Development :: Build Tools
Classifier: License :: OSI Approved :: MIT License
Classifier: Programming Language :: Python :: 2
Classifier: Programming Language :: Python :: 2.7
